{
  "sections": [
    {
      "name": "Rancheros Breakfasts",
      "items": [
        { "name": "Huevos Rancheros", "description": "Huevos Rancheros" },
        { "name": "Carne Adovada Rancheros", "description": "Huevos Rancheros with carne adovada" },
        { "name": "Taco Rancheros", "description": "Huevos Rancheros with seasoned ground beef on corn tortillas" },
        { "name": "Enchilada Rancheros", "description": "Huevos Rancheros with two enchiladas" }
      ]
    },
    {
      "name": "Pollos Breakfasts",
      "items": [
        { "name": "Pollos Classic Breakfast", "description": "Our basic Pollos burrito (Pollos bonus size - add .50 cents), with choice of coffee or orange juice" },
        { "name": "Pollos Chicken Biscuit", "description": "Fried chicken filet on a buttered biscuit" },
        { "name": "Pollos Breakfast Sandwich", "description": "Two eggs, boneless grilled chicken, green chile and salsa served on our classic bun" },
        { "name": "Pollos Breakfast Tacos", "description": "Shredded spiced chicken with eggs, potatoes, green chile and salsa (add cheese - .50 cents more)" }
      ]
    },
    {
      "name": "Pollos Burritos",
      "items": [
        { "name": "Basic", "description": "Egg & potato" },
        { "name": "Westside", "description": "Egg, potato & green chile" },
        { "name": "New Mexico", "description": "Egg, potato, green chile & cheese" },
        { "name": "Albuquerque", "description": "Sausage, egg, potato, red chile & cheese" },
        { "name": "South Valley", "description": "Chorizo, egg, potato, red chile & cheese" },
        { "name": "Taos", "description": "Ham, egg, potato, green chile & cheese" },
        { "name": "Rio Grande", "description": "Carne adovada, egg, potato, red chile & cheese" },
        { "name": "Supreme", "description": "Bacon, egg, potato, red chile & cheese" },
        { "name": "Santa Fe", "description": "Ground beef, egg, potato, onion, red chile & cheese" },
        { "name": "Vegetarian", "description": "Egg, bell pepper, onion, tomato, green chile & cheese" },
        { "name": "Denver", "description": "Egg, ham, bell peppers, onion, & cheese" },
        { "name": "Three Meat Biggie", "description": "Sausage, bacon, ham, egg, potato, green chile, & cheese" }
      ]
    },
    {
      "name": "Side Order",
      "items": [
        {"name": "French Fries"},
        {"name": "Green Chile Cheese Fries", "description": "Topped with chile & cheese"},
        {"name": "Curly Fries", "description": ""},
        {"name": "Taco", "description": "With homemade salsa"},
        {"name": "Enchilada", "description": ""},
        {"name": "Mini Nachos", "description": "Tostados with bean, cheese & jalapeño"},
        {"name": "Chips & Homemade Salsa", "description": ""},
        {"name": "Rice & Beans", "description": ""},
        {"name": "Corn Dog", "description": ""}
      ]
    },
    {
      "name": "Beverages",
      "items": [
        {"name": "Ice Tea", "description": "Sweet and unsweet"},
        {"name": "Coca Cola", "description": ""},
        {"name": "Dr. Pepper", "description": ""},
        {"name": "Diet Coke", "description": ""},
        {"name": "Diet Dr. Pepper", "description": ""},
        {"name": "Barq's Root Beet", "description": ""},
        {"name": "Sprite", "description": ""},
        {"name": "Coffee", "description": ""},
        {"name": "Orange Juice", "description": ""},
        {"name": "Bottled Water", "description": ""}
      ]
    },
    {
      "name": "Desserts",
      "items": [
        {"name": "Apple Bites", "description": ""},
        {"name": "Churros", "description": ""},
        {"name": "Ice Cream", "description": "Cone or cup"},
        {"name": "Shakes", "description": "Chocolate, vanilla, or cherry"},
        {"name": "Root Beer Float", "description": ""}
      ]
    }
  ]
}
